odevgui_win/__init__.py
odevgui_win/class_args/__init__.py
odevgui_win/class_args/send_key_info.py
odevgui_win/data_type/__init__.py
odevgui_win/data_type/rectangle.py
odevgui_win/dialog_auto.py
odevgui_win/draw_dispatcher.py
odevgui_win/exceptions/__init__.py
odevgui_win/focus.py
odevgui_win/keys/__init__.py
odevgui_win/keys/calc_key_codes.py
odevgui_win/keys/draw_key_codes.py
odevgui_win/keys/general.py
odevgui_win/keys/impress_key_codes.py
odevgui_win/keys/writer_key_codes.py
odevgui_win/kind/__init__.py
odevgui_win/kind/keys_kind.py
odevgui_win/robot_keys.py
ooo_dev_tools_gui_win-0.3.2.dist-info/LICENSE
ooo_dev_tools_gui_win-0.3.2.dist-info/METADATA
ooo_dev_tools_gui_win-0.3.2.dist-info/WHEEL
ooo_dev_tools_gui_win-0.3.2.dist-info/RECORD
